ds_capability/__init__.py
ds_capability/components/__init__.py
ds_capability/components/abstract_common_component.py
ds_capability/components/commons.py
ds_capability/components/controller.py
ds_capability/components/discovery.py
ds_capability/components/feature_build.py
ds_capability/components/feature_engineer.py
ds_capability/components/feature_predict.py
ds_capability/components/feature_select.py
ds_capability/components/feature_transform.py
ds_capability/components/pipeline_scripts.py
ds_capability/components/visualization.py
ds_capability/handlers/__init__.py
ds_capability/handlers/cortex_helpers.py
ds_capability/handlers/duckdb_handlers.py
ds_capability/handlers/mc_handlers.py
ds_capability/handlers/mlflow_handlers.py
ds_capability/handlers/mongodb_handlers.py
ds_capability/handlers/mysql_handlers.py
ds_capability/handlers/postgres_handlers.py
ds_capability/handlers/pyarrow_handlers.py
ds_capability/handlers/s3_handlers.py
ds_capability/intent/__init__.py
ds_capability/intent/abstract_feature_build_intent.py
ds_capability/intent/abstract_feature_engineer_intent.py
ds_capability/intent/abstract_feature_intent.py
ds_capability/intent/abstract_feature_predict_intent.py
ds_capability/intent/abstract_feature_select_intent.py
ds_capability/intent/abstract_feature_transform_intent.py
ds_capability/intent/common_intent.py
ds_capability/intent/controller_intent.py
ds_capability/intent/feature_build_intent.py
ds_capability/intent/feature_engineer_intent.py
ds_capability/intent/feature_predict_intent.py
ds_capability/intent/feature_select_intent.py
ds_capability/intent/feature_transform_intent.py
ds_capability/managers/__init__.py
ds_capability/managers/controller_property_manager.py
ds_capability/managers/feature_build_property_manager.py
ds_capability/managers/feature_engineer_property_manager.py
ds_capability/managers/feature_predict_property_manager.py
ds_capability/managers/feature_select_property_manager.py
discovery_capability-0.23.20.dist-info/LICENSE.txt
discovery_capability-0.23.20.dist-info/METADATA
discovery_capability-0.23.20.dist-info/WHEEL
discovery_capability-0.23.20.dist-info/top_level.txt
discovery_capability-0.23.20.dist-info/RECORD
